{
  "main": {
    "id": "3520879aa9c7e3df",
    "type": "split",
    "children": [
      {
        "id": "a89e01e1cbedaef1",
        "type": "tabs",
        "children": [
          {
            "id": "081f2de518230821",
            "type": "leaf",
            "state": {
              "type": "empty",
              "state": {}
            }
          }
        ]
      }
    ],
    "direction": "vertical"
  },
  "left": {
    "id": "f6eb1c0292353f60",
    "type": "split",
    "children": [
      {
        "id": "2e609999d6aeeb1c",
        "type": "tabs",
        "children": [
          {
            "id": "92ea186d3fe3b365",
            "type": "leaf",
            "state": {
              "type": "file-explorer",
              "state": {
                "sortOrder": "alphabetical"
              }
            }
          },
          {
            "id": "0c01e2d9b55b4ebc",
            "type": "leaf",
            "state": {
              "type": "search",
              "state": {
                "query": "tag:#idea",
                "matchingCase": false,
                "explainSearch": false,
                "collapseAll": true,
                "extraContext": false,
                "sortOrder": "alphabetical"
              }
            }
          },
          {
            "id": "364a2c16d2afd5d8",
            "type": "leaf",
            "state": {
              "type": "bookmarks",
              "state": {}
            }
          },
          {
            "id": "6e1743cbe8adfe02",
            "type": "leaf",
            "state": {
              "type": "markdown",
              "state": {
                "file": "3_Files/Essay-Paragraph-1.md",
                "mode": "source",
                "backlinks": true,
                "source": false
              }
            }
          },
          {
            "id": "430bfda880c2ac87",
            "type": "leaf",
            "state": {
              "type": "markdown",
              "state": {
                "file": "3_Files/Essay-Paragraph-2.md",
                "mode": "source",
                "backlinks": true,
                "source": false
              }
            }
          }
        ],
        "currentTab": 1
      }
    ],
    "direction": "horizontal",
    "width": 542.5
  },
  "right": {
    "id": "17d9ef55b4e5bcd6",
    "type": "split",
    "children": [
      {
        "id": "182c6cccc29caec4",
        "type": "tabs",
        "children": [
          {
            "id": "327f0d5c713d363a",
            "type": "leaf",
            "state": {
              "type": "backlink",
              "state": {
                "collapseAll": false,
                "extraContext": false,
                "sortOrder": "alphabetical",
                "showSearch": false,
                "searchQuery": "",
                "backlinkCollapsed": false,
                "unlinkedCollapsed": true
              }
            }
          },
          {
            "id": "3252184b097d8127",
            "type": "leaf",
            "state": {
              "type": "outgoing-link",
              "state": {
                "linksCollapsed": false,
                "unlinkedCollapsed": true
              }
            }
          },
          {
            "id": "a825551ccfda6c5b",
            "type": "leaf",
            "state": {
              "type": "tag",
              "state": {
                "sortOrder": "frequency",
                "useHierarchy": true
              }
            }
          },
          {
            "id": "c96fd0ce0d3fade8",
            "type": "leaf",
            "state": {
              "type": "outline",
              "state": {}
            }
          },
          {
            "id": "d111d17581242978",
            "type": "leaf",
            "state": {
              "type": "advanced-tables-toolbar",
              "state": {}
            }
          },
          {
            "id": "7676528191e4eec1",
            "type": "leaf",
            "state": {
              "type": "git-view",
              "state": {}
            }
          },
          {
            "id": "e3a36cec4704e8fc",
            "type": "leaf",
            "state": {
              "type": "git-history-view",
              "state": {}
            }
          }
        ],
        "currentTab": 5
      }
    ],
    "direction": "horizontal",
    "width": 509.5
  },
  "left-ribbon": {
    "hiddenItems": {
      "switcher:Open quick switcher": false,
      "graph:Open graph view": false,
      "canvas:Create new canvas": false,
      "daily-notes:Open today's daily note": false,
      "templates:Insert template": false,
      "command-palette:Open command palette": false,
      "table-editor-obsidian:Advanced Tables Toolbar": false,
      "templater-obsidian:Templater": false,
      "obsidian-excalidraw-plugin:Create new drawing": false
    }
  },
  "active": "081f2de518230821",
  "lastOpenFiles": [
    "1_Zettelkasten-Echopraxia/Of-greater-concern-are-the-smaller-networks-pioneered-by-the-so-called-Bicameral-Order...no-interest..remain-susceptible-to-weaponization.md",
    "1_Zettelkasten-Echopraxia/Portia-had-learned-to-partition-its-cognitive-processes-almost-as-if-it-were-emulating-a-larger-brain-piece-by-piece-...Slices-of-intellect.md",
    "1_Zettelkasten-Echopraxia/Infectious-zombieism-running-rampant-in-at-least-twenty-countries...Realists-and-Rearguard-Catholics...heretics...Food-poisoning...new-weaponized-echopraxia.md",
    "1_Zettelkasten-Echopraxia/If-the-laws-of-physics-are-part-of-some-universal-operating-system-and-God,-by-definition,-breaks-them…Don’t-stop-now-roach...God’s-a-virus.md",
    "1_Zettelkasten-Echopraxia/But-we-first-gen-types,-we—stayed-awake...didn’t-really-care...thrown-the-world’s-lifeline-into-the-sun-What-I’m-saying-is,-I-was-there.-The-whole-time.md",
    "1_Zettelkasten-Echopraxia/And-he-got-those-augments-because-you-chose-a-certain-line-of-work...took-a-shot-at-you-and-hit-him-instead...You-blame-yourself-for-what-happened-to-your-son.md",
    "1_Zettelkasten-Echopraxia/A-stealth-supernet-fine-tuned-for-the-manipulation-of-pawns-...And-it-just-emerged...Something-must-have-created-it...half-of-him-was-enough.md",
    "3_Files/Excalidraw/DisabilityAndBodyAnxieties.excalidraw",
    "1_Zettelkasten-Echopraxia/Lee,-it’s-not-just-that-these-people-can’t-wrap-their-heads-around-mortality...can’t-even-entertain-the-possibility-they-could-be-wrong...doesn’t-scare-the-shit-out-of-you.md",
    "1_Zettelkasten-Echopraxia/They’re-more-glitchy-than-we-are,-because-half-their-upgrades-are-barely-out-of-beta...They-think-rings-around-us-in-every-way-that-matters..md",
    "1_Zettelkasten-Echopraxia/It-burned-them-out-and-moved-on;-you-could-tell-when-it-had-finished-because-the-convulsions-stopped,-at-long-last,-and-left-nothing-behind-but-vegetation.md",
    "1_Zettelkasten-Echopraxia/Change-alpha-a-just-bit-and-the-universe-stops-supporting-life.-Maybe-alpha’s-wrong.-Maybe-life’s-just-a-parasitic-offshoot-of-a-corrupted-OS.md",
    "1_Zettelkasten-Echopraxia/Something-has-to-tell-the-second-layer-of-atoms-when-to-come-though...Might-as-well-call-it-magic...Hive-calls-it-the-Face-of-God.md",
    "1_Zettelkasten-Echopraxia/He-pulled-the-gimp-hood-over-his-head,-linked-into-the-lab’s-ConSensus-channel,-and-time-just—stopped.-It-stopped,-then-shot-ahead-in-an-instant.md",
    "1_Zettelkasten-Echopraxia/You-see—zombies...less-than-human...Less-than-animals,-maybe;-not-even-conscious.nnnpossible-to-disrespect-something-like-that.-Like-disrespecting-a-lawn-mower.md",
    "1_Zettelkasten-Echopraxia/They-roll-around-on-the-floor-and-ululate-and-you-write-up-the-patent-applications.-We-don’t-know-how-it-works...it-could-stop-working-at-any-moment.md",
    "1_Zettelkasten-Echopraxia/And-from-those-humble-beginnings-we-learned-to-see-faces-in-the-clouds-...to-see-agency-in-randomness,-because-natural-selection-favors-the-paranoid..md",
    "1_Zettelkasten-Echopraxia/Dan,-you-gotta-let-go-of-this-whole-self-thing.-Identity-changes-by-the-second,-you-turn-into-someone-else-every-time-a-new-thought-rewires-your-brain.md",
    "1_Zettelkasten-Echopraxia/It-was-a-breakneck-overgrowth-of-weedy-electricity-that-nearly-killed-its-initiates-outright,-pulled-sixty-million-year-old-circuits-out-by-the-roots..md",
    "1_Zettelkasten-Echopraxia/Vodou-works,-Oldschool.-...Adrenaline-kills-heart-cells.-You-can-literally-scare-someone-to-death-if-you-hack-the-sympathetic-nervous-system-the-right-way.md",
    "1_Zettelkasten-Echopraxia/Just-induced-the-mother-of-all-allergic-responses...Any-kind-of-direct-neural-interface-finishes-what-that-little-bugger-started.-They-could-fix-that.md",
    "1_Zettelkasten-Echopraxia/Szpindel-et-al-‘Gamma-protocadherin-and-the-role-of-the-PCDH11Y-ortholog...Hemineglect...See-why-you-should-get-augged.md",
    "1_Zettelkasten-Echopraxia/Sengupta-liked-Daniel-Brüks-because-he-was-easy-to-impress.-She-didn’t-think-of-him-as-a-person-at-all;-she-thought-of-him-as-a-kind-of-pet..md",
    "1_Zettelkasten-Echopraxia/It-didn’t-matter-what-bedtime-stories-these-privileged-brats-had-been-told.-They-were-not-immortal-in-such-a-presence.-They-were-only-breakfast..md",
    "1_Zettelkasten-Echopraxia/She’s-just-another-failed-hominoid....Without-our-drugs-she-couldn’t-even-handle-a-few-right-angles...Just-another-one-of-nature’s-fuckups.md",
    "1_Zettelkasten-Echopraxia/I’m saying we all are. Next to the hives, and the vampires...—We’re children...can’t be trusted to make our own decisions...Have a drink...Helps the future go down easier.md",
    "1_Zettelkasten-Echopraxia/Valerie began to convulse. She tried to arch her back...Fireworks exploded across her brain. Her heart, so immutably stable until now, threw jagged spikes...shut down completely.md",
    "2_ReferenceNotes/DashFormatter.py",
    "2_ReferenceNotes/Blindsight-SpaceRemover.py",
    "1_Zettelkasten",
    "2_ReferenceNotes/Echopraxia-Chapter.py",
    "3_Files/Pasted Image 20230504191016_980.jpg",
    "3_Files/Pasted image 20230504195430.jpg",
    "3_Files/Pasted image 20230504192705.jpg",
    "3_Files/Pasted image 20230504192820.jpg",
    "1_Zettelkasten-Echopraxia",
    "Excalidraw/DisabilityAndBodyAnxieties.excalidraw.crswap",
    "Untitled 1.canvas",
    "Untitled.canvas",
    "Blindsight.canvas",
    "2-25.canvas",
    "3_Files/Excalidraw",
    "Untitled 2.canvas",
    "Untitled 3.canvas",
    "4_Templates",
    "3_Files"
  ]
}